buddy/__init__.py
buddy/constants.py
buddy/debug.py
buddy/exceptions.py
buddy/media.py
buddy/py.typed
buddy/agent/__init__.py
buddy/agent/agent.py
buddy/agent/evolution.py
buddy/agent/metrics.py
buddy/agent/personality.py
buddy/api/__init__.py
buddy/api/agent.py
buddy/api/api.py
buddy/api/app.py
buddy/api/evals.py
buddy/api/playground.py
buddy/api/routes.py
buddy/api/team.py
buddy/api/user.py
buddy/api/workflows.py
buddy/api/workspace.py
buddy/api/schemas/__init__.py
buddy/api/schemas/agent.py
buddy/api/schemas/app.py
buddy/api/schemas/evals.py
buddy/api/schemas/playground.py
buddy/api/schemas/response.py
buddy/api/schemas/team.py
buddy/api/schemas/user.py
buddy/api/schemas/workflows.py
buddy/api/schemas/workspace.py
buddy/app/__init__.py
buddy/app/base.py
buddy/app/settings.py
buddy/app/utils.py
buddy/app/agui/__init__.py
buddy/app/agui/app.py
buddy/app/agui/async_router.py
buddy/app/agui/sync_router.py
buddy/app/agui/utils.py
buddy/app/discord/__init__.py
buddy/app/discord/client.py
buddy/app/fastapi/__init__.py
buddy/app/fastapi/app.py
buddy/app/fastapi/async_router.py
buddy/app/fastapi/sync_router.py
buddy/app/playground/__init__.py
buddy/app/playground/app.py
buddy/app/playground/async_router.py
buddy/app/playground/deploy.py
buddy/app/playground/operator.py
buddy/app/playground/schemas.py
buddy/app/playground/serve.py
buddy/app/playground/settings.py
buddy/app/playground/sync_router.py
buddy/app/playground/utils.py
buddy/app/slack/__init__.py
buddy/app/slack/app.py
buddy/app/slack/async_router.py
buddy/app/slack/security.py
buddy/app/slack/sync_router.py
buddy/app/whatsapp/__init__.py
buddy/app/whatsapp/app.py
buddy/app/whatsapp/async_router.py
buddy/app/whatsapp/security.py
buddy/app/whatsapp/sync_router.py
buddy/cli/__init__.py
buddy/cli/auth_server.py
buddy/cli/config.py
buddy/cli/console.py
buddy/cli/credentials.py
buddy/cli/entrypoint.py
buddy/cli/operator.py
buddy/cli/settings.py
buddy/cli/simple_train_cli.py
buddy/cli/train_cli.py
buddy_ai-1.0.6.dist-info/licenses/LICENSE
buddy_ai-1.0.6.dist-info/METADATA
buddy_ai-1.0.6.dist-info/WHEEL
buddy_ai-1.0.6.dist-info/entry_points.txt
buddy_ai-1.0.6.dist-info/top_level.txt
buddy_ai-1.0.6.dist-info/RECORD
