Metadata-Version: 2.4
Name: buddy-ai
Version: 1.0.6
Summary: A comprehensive Python framework for building and deploying AI agents with multi-model support and advanced capabilities
Author-email: Sriram Sangeeth Mantha <sriram.sangeet@gmail.com>
Maintainer-email: Sriram Sangeeth Mantha <sriram.sangeet@gmail.com>
License-Expression: MIT
Project-URL: Homepage, https://github.com/esasrir91/buddy-ai
Project-URL: Documentation, https://esasrir91.github.io/buddy-ai/
Project-URL: Repository, https://github.com/esasrir91/buddy-ai
Project-URL: Bug Reports, https://github.com/esasrir91/buddy-ai/issues
Project-URL: Discussions, https://github.com/esasrir91/buddy-ai/discussions
Project-URL: Release Notes, https://github.com/esasrir91/buddy-ai/releases
Keywords: ai,agents,llm,chatbot,artificial-intelligence,machine-learning,nlp,openai,anthropic,rag,multi-agent,workflow,automation,ai-framework,conversational-ai,intelligent-agents,ai-assistant
Classifier: Development Status :: 5 - Production/Stable
Classifier: Intended Audience :: Developers
Classifier: Intended Audience :: Science/Research
Classifier: Operating System :: OS Independent
Classifier: Programming Language :: Python :: 3
Classifier: Programming Language :: Python :: 3.10
Classifier: Programming Language :: Python :: 3.11
Classifier: Programming Language :: Python :: 3.12
Classifier: Programming Language :: Python :: 3.13
Classifier: Topic :: Scientific/Engineering :: Artificial Intelligence
Classifier: Topic :: Software Development :: Libraries :: Python Modules
Classifier: Topic :: Software Development :: Libraries :: Application Frameworks
Classifier: Environment :: Console
Classifier: Environment :: Web Environment
Requires-Python: >=3.10
License-File: LICENSE
Requires-Dist: pydantic>=2.0.0
Requires-Dist: pydantic-settings>=2.0.0
Requires-Dist: httpx>=0.24.0
Requires-Dist: fastapi>=0.100.0
Requires-Dist: uvicorn>=0.23.0
Requires-Dist: typer>=0.9.0
Requires-Dist: rich>=13.0.0
Requires-Dist: python-multipart>=0.0.6
Requires-Dist: starlette>=0.27.0
Requires-Dist: docstring-parser>=0.15
Requires-Dist: packaging>=23.0
Requires-Dist: openai>=1.0.0
Requires-Dist: streamlit>=1.28.0
Requires-Dist: spacy>=3.4.0
Requires-Dist: numpy>=1.21.0
Requires-Dist: scikit-learn>=1.1.0
Provides-Extra: dev
Requires-Dist: pytest>=7.0.0; extra == "dev"
Requires-Dist: pytest-asyncio>=0.21.0; extra == "dev"
Requires-Dist: black>=23.0.0; extra == "dev"
Requires-Dist: isort>=5.12.0; extra == "dev"
Requires-Dist: flake8>=6.0.0; extra == "dev"
Requires-Dist: mypy>=1.5.0; extra == "dev"
Provides-Extra: openai
Requires-Dist: openai>=1.0.0; extra == "openai"
Provides-Extra: anthropic
Requires-Dist: anthropic>=0.25.0; extra == "anthropic"
Provides-Extra: google
Requires-Dist: google-generativeai>=0.3.0; extra == "google"
Provides-Extra: cohere
Requires-Dist: cohere>=4.0.0; extra == "cohere"
Provides-Extra: aws
Requires-Dist: boto3>=1.34.0; extra == "aws"
Provides-Extra: azure
Requires-Dist: openai>=1.0.0; extra == "azure"
Provides-Extra: irag
Requires-Dist: spacy>=3.4.0; extra == "irag"
Requires-Dist: numpy>=1.21.0; extra == "irag"
Requires-Dist: scikit-learn>=1.1.0; extra == "irag"
Provides-Extra: all
Requires-Dist: openai>=1.0.0; extra == "all"
Requires-Dist: anthropic>=0.25.0; extra == "all"
Requires-Dist: google-generativeai>=0.3.0; extra == "all"
Requires-Dist: cohere>=4.0.0; extra == "all"
Requires-Dist: boto3>=1.34.0; extra == "all"
Requires-Dist: spacy>=3.4.0; extra == "all"
Requires-Dist: numpy>=1.21.0; extra == "all"
Requires-Dist: scikit-learn>=1.1.0; extra == "all"
Dynamic: license-file
